ndvi2gif/__init__.py
ndvi2gif/clasification.py
ndvi2gif/ndvi2gif.py
ndvi2gif/s1_ard.py
ndvi2gif/timeseries.py
ndvi2gif-1.0.0.dist-info/licenses/LICENSE.txt
tests/__init__.py
tests/conftest.py
tests/test_basic.py
ndvi2gif-1.0.0.dist-info/METADATA
ndvi2gif-1.0.0.dist-info/WHEEL
ndvi2gif-1.0.0.dist-info/top_level.txt
ndvi2gif-1.0.0.dist-info/RECORD
