Metadata-Version: 2.4
Name: ndvi2gif
Version: 1.0.0
Summary: Multi-seasonal remote sensing analysis suite: composites, SAR preprocessing, time series analytics, and land cover classification with Google Earth Engine
Home-page: https://github.com/Digdgeo/Ndvi2Gif
Author: Diego García Díaz
Author-email: diegogarcia@ebd.csic.es
License: MIT
Classifier: Programming Language :: Python :: 3
Classifier: Programming Language :: Python :: 3.8
Classifier: Programming Language :: Python :: 3.9
Classifier: Programming Language :: Python :: 3.10
Classifier: Programming Language :: Python :: 3.11
Classifier: Programming Language :: Python :: 3.12
Classifier: License :: OSI Approved :: MIT License
Classifier: Operating System :: OS Independent
Classifier: Intended Audience :: Science/Research
Classifier: Topic :: Scientific/Engineering :: GIS
Classifier: Topic :: Scientific/Engineering :: Image Processing
Requires-Python: >=3.8
License-File: LICENSE.txt
Requires-Dist: geemap>=0.29.5
Requires-Dist: earthengine-api>=0.1.347
Requires-Dist: numpy<2.0
Requires-Dist: pandas
Requires-Dist: scipy
Requires-Dist: matplotlib
Requires-Dist: seaborn
Requires-Dist: pillow
Requires-Dist: imageio
Requires-Dist: tqdm
Requires-Dist: requests
Requires-Dist: geopandas
Requires-Dist: fiona
Requires-Dist: pycrs
Requires-Dist: deims>=4.0
Requires-Dist: statsmodels>=0.13
Requires-Dist: scikit-learn>=1.0
Provides-Extra: dev
Requires-Dist: black; extra == "dev"
Requires-Dist: isort; extra == "dev"
Requires-Dist: ruff; extra == "dev"
Requires-Dist: pytest; extra == "dev"
Requires-Dist: jupyter; extra == "dev"
Dynamic: license-file
